zeroconf/__init__.py
zeroconf/_cache.py
zeroconf/_core.py
zeroconf/_dns.py
zeroconf/_engine.py
zeroconf/_exceptions.py
zeroconf/_handlers/__init__.py
zeroconf/_handlers/answers.py
zeroconf/_handlers/multicast_outgoing_queue.py
zeroconf/_handlers/query_handler.py
zeroconf/_handlers/record_manager.py
zeroconf/_history.py
zeroconf/_listener.py
zeroconf/_logger.py
zeroconf/_protocol/__init__.py
zeroconf/_protocol/incoming.py
zeroconf/_protocol/outgoing.py
zeroconf/_record_update.py
zeroconf/_services/__init__.py
zeroconf/_services/browser.py
zeroconf/_services/info.py
zeroconf/_services/registry.py
zeroconf/_services/types.py
zeroconf/_transport.py
zeroconf/_updates.py
zeroconf/_utils/__init__.py
zeroconf/_utils/asyncio.py
zeroconf/_utils/ipaddress.py
zeroconf/_utils/name.py
zeroconf/_utils/net.py
zeroconf/_utils/time.py
zeroconf/asyncio.py
zeroconf/const.py
zeroconf/py.typed
open_stage_zeroconf-0.132.2.dev0.dist-info/COPYING
open_stage_zeroconf-0.132.2.dev0.dist-info/METADATA
open_stage_zeroconf-0.132.2.dev0.dist-info/WHEEL
open_stage_zeroconf-0.132.2.dev0.dist-info/RECORD
